LICENSE
MANIFEST.in
README.rst
setup.cfg
setup.py
versioneer.py
artellapipe/__init__.py
artellapipe/launcher/__init__.py
artellapipe/launcher/__logging__.ini
artellapipe/launcher/__version__.py
artellapipe/launcher/_version.py
artellapipe/launcher/loader.py
artellapipe/launcher/register.py
artellapipe/launcher/core/__init__.py
artellapipe/launcher/core/defines.py
artellapipe/launcher/core/launcher.py
artellapipe/launcher/core/plugin.py
artellapipe/launcher/plugins/__init__.py
artellapipe/launcher/resources/icons/color/artella.png
artellapipe/launcher/resources/icons/color/console.png
artellapipe/launcher/resources/icons/color/home.png
artellapipe/launcher/resources/icons/color/plugin.png
artellapipe/launcher/resources/icons/color/search_folder.png
artellapipe/launcher/resources/icons/color/uninstall.png
artellapipe/launcher/resources/icons/default/artella.png
artellapipe/launcher/resources/icons/default/artellamanager_plugin.png
artellapipe/launcher/resources/icons/default/console.png
artellapipe/launcher/resources/icons/default/home.png
artellapipe/launcher/resources/icons/default/launcher.png
artellapipe/launcher/resources/icons/default/plugin.png
artellapipe/launcher/resources/icons/default/search_folder.png
artellapipe/launcher/resources/icons/default/uninstall.png
artellapipe/launcher/resources/images/launcher_logo.png
artellapipe/launcher/resources/images/splash.png
artellapipe/launcher/resources/psd/artellalauncher_splash.psd
artellapipe/launcher/utils/__init__.py
artellapipe/launcher/utils/download.py
artellapipe/launcher/widgets/__init__.py
artellapipe/launcher/widgets/console.py
artellapipe/launcher/widgets/pluginspanel.py
artellapipe/launcher/widgets/waitconnection.py
artellapipe_launcher.egg-info/PKG-INFO
artellapipe_launcher.egg-info/SOURCES.txt
artellapipe_launcher.egg-info/dependency_links.txt
artellapipe_launcher.egg-info/not-zip-safe
artellapipe_launcher.egg-info/requires.txt
artellapipe_launcher.egg-info/top_level.txt
tests/__init__.py
tests/test_general.py