Metadata-Version: 2.1
Name: artellapipe-launcher
Version: 0.0.23
Summary: Artella Launcher can be used to create Artella based project launchers
Home-page: UNKNOWN
Author: Tomas Poveda
Author-email: tpovedatd@gmail.com
License: MIT
Platform: UNKNOWN
Provides-Extra: dev
Provides-Extra: test
